addressrec/__init__.py
addressrec-0.0.14.dist-info/LICENSE
addressrec-0.0.14.dist-info/METADATA
addressrec-0.0.14.dist-info/WHEEL
addressrec-0.0.14.dist-info/top_level.txt
addressrec-0.0.14.dist-info/RECORD
