Metadata-Version: 2.1
Name: addressrec
Version: 0.0.14
Summary: 字符串智能解析，解析省市区、姓名、电话
Author-email: zhichao wang <wzc570738205@gmail.com>
Project-URL: Source, https://github.com/wzc570738205/smartParsePro-py
Requires-Python: >=3.0
License-File: LICENSE
Requires-Dist: jionlp
Requires-Dist: jieba
Requires-Dist: Levenshtein
Requires-Dist: paddlepaddle ==2.4.2
